{
	"cast":               "panda.mvc.validator.CastErrorFieldValidator",
	"required":           "panda.mvc.validator.RequiredFieldValidator",
	"empty":              "panda.mvc.validator.EmptyFieldValidator",
	
	"el":                 "panda.mvc.validator.ElFieldValidator",
	"regex":              "panda.mvc.validator.RegexFieldValidator",
	"email":              "panda.mvc.validator.EmailFieldValidator",
	"filename":           "panda.mvc.validator.FilenameFieldValidator",
	"creditcardno":       "panda.mvc.validator.CreditCardNumberFieldValidator",
	
	"binary":             "panda.mvc.validator.BinaryFieldValidator",
	"date":               "panda.mvc.validator.DateFieldValidator",
	"number":             "panda.mvc.validator.NumberFieldValidator",
	"string":             "panda.mvc.validator.StringFieldValidator",
	"decimal":            "panda.mvc.validator.DecimalFieldValidator",
	
	"file":               "panda.mvc.validator.FileFieldValidator",
	"image":              "panda.mvc.validator.ImageFieldValidator",
	
	"constant":           "panda.mvc.validator.ConstantFieldValidator",
	"prohibited":         "panda.mvc.validator.ProhibitedFieldValidator",
	
	"visitor":            "panda.mvc.validator.VisitorFieldValidator"
}
